{
  "$schema": "https://developer.microsoft.com/json-schemas/fabric/item/report/definition/visualContainer/1.0.0/schema.json",
  "name": "slicerDate",
  "position": {
    "x": 790,
    "y": 440,
    "z": 25,
    "width": 480,
    "height": 100,
    "tabOrder": 25000
  },
  "visual": {
    "visualType": "slicer",
    "query": {
      "queryState": {
        "Values": {
          "projections": [
            {
              "field": {
                "Column": {
                  "Expression": {
                    "SourceRef": {
                      "Entity": "DateTable"
                    }
                  },
                  "Property": "Date"
                }
              },
              "queryRef": "DateTable.Date",
              "nativeQueryRef": "Date"
            }
          ]
        }
      }
    },
    "objects": {}
  }
}
